{"id":8575,"name":"Buğra Arkın","ign":"Calyx","image":"https://img-cdn.hltv.org/playerbodyshot/OyFUlrBnQnSL0xCmQcDcex.png?ixlib=java-2.1.0&w=400&s=c1efc65831ac6be77c28b8de4e3d2bc2","age":27,"twitch":"https://www.twitch.tv/calyxba","instagram":"https://www.instagram.com/calyxcs","country":{"name":"Turkey","code":"TR"},"team":{"name":"Eternal Fire","id":11251},"statistics":{"rating":1.08,"killsPerRound":null,"headshots":null,"mapsPlayed":null,"deathsPerRound":null,"roundsContributed":null},"achievements":[{"place":"1/4 final","event":{"name":"PGL CS2 Major Copenhagen 2024","id":7148}},{"place":"Challengers","event":{"name":"PGL Major Antwerp 2022 Challengers Stage","id":6384}},{"place":"Challengers","event":{"name":"FACEIT Major 2018 Challengers Stage","id":3885}},{"place":"Legends","event":{"name":"ELEAGUE Major 2018","id":3247}},{"place":"2nd","event":{"name":"ESL Pro League Season 20","id":7441}},{"place":"2nd","event":{"name":"BetBoom Dacha Belgrade Season 2","id":7993}},{"place":"2nd","event":{"name":"ESL Challenger Jönköping 2023","id":6868}},{"place":"2nd","event":{"name":"WESG 2017 World Finals","id":3112}}],"teams":[{"id":11251,"name":"Eternal Fire","startDate":1746914400000,"trophies":[]},{"id":10333,"name":"Sangal","startDate":1738191600000,"leaveDate":1745359200000,"trophies":[]},{"id":11251,"name":"Eternal Fire","startDate":1667775600000,"leaveDate":1738191600000,"trophies":[]},{"id":11540,"name":"Benched Heroes","startDate":1661464800000,"leaveDate":1664402400000,"trophies":[]},{"id":11251,"name":"Eternal Fire","startDate":1628805600000,"leaveDate":1656885600000,"trophies":[]},{"id":11102,"name":"GORILLAZ","startDate":1618264800000,"leaveDate":1619128800000,"trophies":[]},{"id":5991,"name":"Envy","startDate":1580425200000,"leaveDate":1614207600000,"trophies":[]},{"id":8513,"name":"Windigo","startDate":1562709600000,"leaveDate":1571695200000,"trophies":[]},{"id":9572,"name":"ex-Space Soldiers","startDate":1539640800000,"leaveDate":1555279200000,"trophies":[]},{"id":5929,"name":"Space Soldiers","startDate":1486940400000,"leaveDate":1539381600000,"trophies":[]},{"id":7607,"name":"ex-DarkPassage","startDate":1485903600000,"leaveDate":1486940400000,"trophies":[]},{"id":7018,"name":"DarkPassage","startDate":1464732000000,"leaveDate":1485903600000,"trophies":[]},{"id":6629,"name":"Deathtrap","startDate":1452380400000,"leaveDate":1464732000000,"trophies":[]}],"news":[{"name":"Short: EMSTAR returns to Eternal Fire","link":"/news/43107/short-news-week-45#f15"},{"name":"Short: Eternal Fire promote rim3","link":"/news/42743/short-news-week-39#f22"},{"name":"Eternal Fire overhaul team with ex-Sangal core","link":"/news/42163/eternal-fire-overhaul-team-with-ex-sangal-core"},{"name":"Short: Eternal Fire bench trio","link":"/news/42126/short-news-week-28#f20"},{"name":"Hastr0: Envy \"already scouting\" potential CS2 rosters","link":"/news/42094/hastr0-envy-already-scouting-potential-cs2-rosters"},{"name":"Eternal Fire reveal new roster","link":"/news/41660/eternal-fire-reveal-new-roster"},{"name":"Short: Calyx leaves Sangal after benching","link":"/news/41491/short-news-week-17#f12"},{"name":"Sangal bench Calyx and kreaz to recreate former Permitta core","link":"/news/41256/sangal-bench-calyx-and-kreaz-to-recreate-former-permitta-core"},{"name":"Fabre: \"When I came to this team, I promised XANTARES he would make the top 20\"","link":"/news/40941/fabre-when-i-came-to-this-team-i-promised-xantares-he-would-make-the-top-20"},{"name":"Eternal Fire secure Katowice playoff berth after instant classic Nuke thriller vs. FaZe","link":"/news/40928/eternal-fire-secure-katowice-playoff-berth-after-instant-classic-nuke-thriller-vs-faze"},{"name":"Team ranking: January 2025","link":"/news/40918/team-ranking-january-2025"},{"name":"Calyx, danistzz headline new Sangal roster","link":"/news/40878/calyx-danistzz-headline-new-sangal-roster"},{"name":"MAJ3R on winning with XANTARES having a quiet day: \"That means we are a team now\"","link":"/news/40840/maj3r-on-winning-with-xantares-having-a-quiet-day-that-means-we-are-a-team-now"},{"name":"Eternal Fire stamp out Vitality at BLAST Bounty","link":"/news/40831/eternal-fire-stamp-out-vitality-at-blast-bounty"},{"name":"jottAAA replaces Calyx on Eternal Fire","link":"/news/40655/jottaaa-replaces-calyx-on-eternal-fire"},{"name":"Top 20 players of 2024: XANTARES (15)","link":"/news/40641/top-20-players-of-2024-xantares-15"},{"name":"Short: Eternal Fire CEO comments on roster rumors","link":"/news/40393/short-news-week-48#f4"},{"name":"Astralis eliminate Eternal Fire from EU RMR","link":"/news/40374/astralis-eliminate-eternal-fire-from-eu-rmr"},{"name":"FalleN records personal best LAN map rating in Dacha loss to Eternal Fire","link":"/news/39753/fallen-records-personal-best-lan-map-rating-in-dacha-loss-to-eternal-fire"},{"name":"Eternal Fire in trouble after 0-2 start to YaLLa Compass","link":"/news/39162/eternal-fire-in-trouble-after-0-2-start-to-yalla-compass"},{"name":"Sashi defeat Cloud9 and Eternal Fire in shock EWC qualification run","link":"/news/38820/sashi-defeat-cloud9-and-eternal-fire-in-shock-ewc-qualification-run"},{"name":"Eternal Fire defeat GamerLegion to qualify for Elimination Stage","link":"/news/38531/eternal-fire-defeat-gamerlegion-to-qualify-for-elimination-stage"},{"name":"MAJ3R's hopes of captaining the Turkish ship to the high seas of tier-one CS","link":"/news/38497/maj3rs-hopes-of-captaining-the-turkish-ship-to-the-high-seas-of-tier-one-cs"},{"name":"Meet PGL Copenhagen Major's 34 rookies","link":"/news/38463/meet-pgl-copenhagen-majors-34-rookies"},{"name":"Eternal Fire ravage BetBoom to earn Major berth","link":"/news/38254/eternal-fire-ravage-betboom-to-earn-major-berth"},{"name":"FaZe qualify for the Major in Copenhagen","link":"/news/38239/faze-qualify-for-the-major-in-copenhagen"},{"name":"Five teams we wish were erased from our memory","link":"/news/37635/five-teams-we-wish-were-erased-from-our-memory"},{"name":"Monte win ESL Challenger Jönköping undefeated","link":"/news/37608/monte-win-esl-challenger-jnkping-undefeated"},{"name":"9 Pandas beat Eternal Fire to win PARI Please","link":"/news/37547/9-pandas-beat-eternal-fire-to-win-pari-please"},{"name":"Eternal Fire pick up fourth consecutive 2-0 win en route to EPL quarter-finals","link":"/news/37127/eternal-fire-pick-up-fourth-consecutive-2-0-win-en-route-to-epl-quarter-finals"},{"name":"Eternal Fire eliminate Astralis in first round of EPL playoffs","link":"/news/37116/eternal-fire-eliminate-astralis-in-first-round-of-epl-playoffs"},{"name":"Watch: Calyx ace sets EF up for victory on Vertigo","link":"/news/37114/esl-pro-league-playoffs-round-1-highlights#f8"},{"name":"woxic returns to Eternal Fire","link":"/news/36204/woxic-returns-to-eternal-fire"},{"name":"EU RMR B: Day three as it happened","link":"/news/36041/eu-rmr-b-day-three-as-it-happened"},{"name":"EU RMR B: Day one as it happened","link":"/news/36009/eu-rmr-b-day-one-as-it-happened"},{"name":"Europe RMR B in bullet points: Three things to know about each team","link":"/news/36004/europe-rmr-b-in-bullet-points-three-things-to-know-about-each-team"},{"name":"Team Ranking: February 2023","link":"/news/35756/team-ranking-february-2023"},{"name":"fnatic defeat Eternal Fire 2-1 to grab final Group A playoff berth","link":"/news/35715/fnatic-defeat-eternal-fire-2-1-to-grab-final-group-a-playoff-berth"},{"name":"fnatic relegate Eternal Fire to the Last Chance bracket at EPL","link":"/news/35701/fnatic-relegate-eternal-fire-to-the-last-chance-bracket-at-epl"},{"name":"Eternal Fire send Evil Geniuses to last chance bracket","link":"/news/35692/eternal-fire-send-evil-geniuses-to-last-chance-bracket"},{"name":"Bad News Eagles advance to CCT Central Europe Finals title decider","link":"/news/35663/bad-news-eagles-advance-to-cct-central-europe-finals-title-decider"},{"name":"CCT Central Europe Malta Finals viewer's guide","link":"/news/35607/cct-central-europe-malta-finals-viewers-guide"},{"name":"MAJ3R returns to Eternal Fire","link":"/news/35111/maj3r-returns-to-eternal-fire"},{"name":"CCT Central Europe Series 3 reaches playoffs; Eternal Fire, forZe among invites","link":"/news/35078/cct-central-europe-series-3-reaches-playoffs-eternal-fire-forze-among-invites"},{"name":"Eternal Fire begin rebuild with Calyx return","link":"/news/35030/eternal-fire-begin-rebuild-with-calyx-return"},{"name":"Teams in doubt arrive with complete rosters in time for Europe RMRs","link":"/news/34688/teams-in-doubt-arrive-with-complete-rosters-in-time-for-europe-rmrs"},{"name":"Benched Heroes miss out on RMR","link":"/news/34664/benched-heroes-miss-out-on-rmr"},{"name":"Aunkere set to miss out on RMR; Benched Heroes attendance in doubt","link":"/news/34651/aunkere-set-to-miss-out-on-rmr-benched-heroes-attendance-in-doubt"},{"name":"Visa issues threaten Russian attendance ahead of European RMRs","link":"/news/34635/visa-issues-threaten-russian-attendance-ahead-of-european-rmrs"},{"name":"The 2022 off-season roster shuffle recap","link":"/news/34379/the-2022-off-season-roster-shuffle-recap"},{"name":"Eternal Fire add paz, hardstyle in place of xfl0ud, bishop","link":"/news/34248/eternal-fire-add-paz-hardstyle-in-place-of-xfl0ud-bishop"},{"name":"MAJ3R returns to CS:GO with Eternal Fire","link":"/news/34216/maj3r-returns-to-csgo-with-eternal-fire"},{"name":"Calyx exits Eternal Fire","link":"/news/34172/calyx-exits-eternal-fire"},{"name":"BIG through to Roobet Cup semi-finals over Eternal Fire","link":"/news/34134/big-through-to-roobet-cup-semi-finals-over-eternal-fire"},{"name":"Eternal Fire eliminate Imperial from Roobet Cup","link":"/news/34124/eternal-fire-eliminate-imperial-from-roobet-cup"},{"name":"xfl0ud to miss weeks of action as Eternal Fire call up academy member colorzz","link":"/news/33220/xfl0ud-to-miss-weeks-of-action-as-eternal-fire-call-up-academy-member-colorzz"},{"name":"The 2022 rostermania recap","link":"/news/33078/the-2022-rostermania-recap"},{"name":"Eternal Fire bench Calyx, duggyversus to step in","link":"/news/33156/eternal-fire-bench-calyx-duggyversus-to-step-in"},{"name":"fnatic defeat Eternal Fire to claim REPUBLEAGUE TIPOS Season 2 title","link":"/news/32831/fnatic-defeat-eternal-fire-to-claim-republeague-tipos-season-2-title"},{"name":"Pinnacle Fall Series 2 Regionals fantasy game live","link":"/news/32472/pinnacle-fall-series-2-regionals-fantasy-game-live"},{"name":"Rostermania update: Off-season changes in one place*","link":"/news/32140/rostermania-update-off-season-changes-in-one-place"},{"name":"Turkish superteam goes official as Eternal Fire; ISSAA joins as fifth","link":"/news/32166/turkish-superteam-goes-official-as-eternal-fire-issaa-joins-as-fifth"},{"name":"XANTARES released from BIG contract","link":"/news/32161/xantares-released-from-big-contract"},{"name":"xfl0ud steps down from GORILLAZ","link":"/news/32151/xfl0ud-steps-down-from-gorillaz"},{"name":"EspiranTo exits GORILLAZ","link":"/news/31774/espiranto-exits-gorillaz"},{"name":"Calyx parts ways with GORILLAZ","link":"/news/31619/calyx-parts-ways-with-gorillaz"},{"name":"suNny, flusha team up in new international roster","link":"/news/31542/sunny-flusha-team-up-in-new-international-roster"},{"name":"Thomas announces free agency","link":"/news/31270/thomas-announces-free-agency"},{"name":"Calyx leaves Envy","link":"/news/31266/calyx-leaves-envy"},{"name":"MICHU leaves Envy","link":"/news/31251/michu-leaves-envy"},{"name":"Envy to put CS:GO division on hold*","link":"/news/30948/envy-to-put-csgo-division-on-hold"},{"name":"forZe defeat Envy in Flashpoint 2 Group B opening match","link":"/news/30610/forze-defeat-envy-in-flashpoint-2-group-b-opening-match"},{"name":"Envy release moose and ryann, add kuben as head coach; LEGIJA transitions to player","link":"/news/30070/envy-release-moose-and-ryann-add-kuben-as-head-coach-legija-transitions-to-player"},{"name":"'MICHU safe in Envy' - Agent","link":"/news/30007/michu-safe-in-envy-agent"},{"name":"Envy in talks to make multiple changes to roster - Report","link":"/news/30003/envy-in-talks-to-make-multiple-changes-to-roster-report"},{"name":"Envy upset Liquid in Road to Rio","link":"/news/29546/envy-upset-liquid-in-road-to-rio"},{"name":"moose returns to Envy for Flashpoint Phase 2","link":"/news/29337/moose-returns-to-envy-for-flashpoint-phase-2"},{"name":"MIBR move on in Flashpoint Phase 1; Envy eliminated","link":"/news/29295/mibr-move-on-in-flashpoint-phase-1-envy-eliminated"},{"name":"Gen.G surpass Envy in Los Angeles","link":"/news/29262/geng-surpass-envy-in-los-angeles"},{"name":"LEGIJA to stand in for Envy in Flashpoint","link":"/news/29250/legija-to-stand-in-for-envy-in-flashpoint"},{"name":"Triumph, Envy claim final Americas Minor spots","link":"/news/29239/triumph-envy-claim-final-americas-minor-spots"},{"name":"Envy becomes seventh founding member of FLASHPOINT","link":"/news/29207/envy-becomes-seventh-founding-member-of-flashpoint"},{"name":"ANDROID announces free agency","link":"/news/29135/android-announces-free-agency"},{"name":"FugLy leaves Envy","link":"/news/29133/fugly-leaves-envy"},{"name":"Envy, Rugratz through to Americas Minor NA closed qualifier","link":"/news/28965/envy-rugratz-through-to-americas-minor-na-closed-qualifier"},{"name":"Envy confirm addition of new quartet","link":"/news/28951/envy-confirm-addition-of-new-quartet"},{"name":"moose joins Calyx, MICHU on Envy ESEA roster for ESL One Rio Major open qualifier","link":"/news/28938/moose-joins-calyx-michu-on-envy-esea-roster-for-esl-one-rio-major-open-qualifier"},{"name":"MICHU to join Envy - Report","link":"/news/28921/michu-to-join-envy-report"},{"name":"Envy bench FugLy","link":"/news/28846/envy-bench-fugly"},{"name":"Top 20 players of 2019: woxic (12)","link":"/news/28800/top-20-players-of-2019-woxic-12"},{"name":"mertz announces free agency","link":"/news/28329/mertz-announces-free-agency"},{"name":"Calyx departs Windigo","link":"/news/28207/calyx-departs-windigo"},{"name":"Natus Vincere defeat Windigo; G2 overcome HellRaisers at ESL Pro League","link":"/news/28176/natus-vincere-defeat-windigo-g2-overcome-hellraisers-at-esl-pro-league"},{"name":"mirbit joins Windigo on trial","link":"/news/27879/mirbit-joins-windigo-on-trial"},{"name":"Windigo transfer list SHiPZ","link":"/news/27753/windigo-transfer-list-shipz"},{"name":"Four teams join European Champions Cup participants' list","link":"/news/27558/four-teams-join-european-champions-cup-participants-list"},{"name":"Windigo to play ESL Pro League Relegation with blocker and v1c7or","link":"/news/27553/windigo-to-play-esl-pro-league-relegation-with-blocker-and-v1c7or"},{"name":"Windigo pick up Calyx, hAdji","link":"/news/27308/windigo-pick-up-calyx-hadji"},{"name":"bubble: \"By the end of the year we want to be a top 10 team, that is our main goal\"","link":"/news/27102/bubble-by-the-end-of-the-year-we-want-to-be-a-top-10-team-that-is-our-main-goal"},{"name":"v1c7or: \"It's not easy for Calyx to learn [our system], but still I think we will do great here\"","link":"/news/26928/v1c7or-its-not-easy-for-calyx-to-learn-our-system-but-still-i-think-we-will-do-great-here"},{"name":"Windigo oust TYLOO, FaZe through to playoffs over NiP","link":"/news/26922/windigo-oust-tyloo-faze-through-to-playoffs-over-nip"},{"name":"FaZe beat Windigo; NiP take out TYLOO in Dallas","link":"/news/26914/faze-beat-windigo-nip-take-out-tyloo-in-dallas"},{"name":"Six key storylines of DreamHack Masters Dallas","link":"/news/26904/six-key-storylines-of-dreamhack-masters-dallas"},{"name":"Calyx to stand in for Windigo at DreamHack Masters Dallas","link":"/news/26887/calyx-to-stand-in-for-windigo-at-dreamhack-masters-dallas"},{"name":"EU Minor Open Qualifier 1 day one concluded; top 16 teams found","link":"/news/26881/eu-minor-open-qualifier-1-day-one-concluded-top-16-teams-found"},{"name":"Calyx: \"Nobody knows the scale of the problems we had in Space Soldiers\"","link":"/news/26678/calyx-nobody-knows-the-scale-of-the-problems-we-had-in-space-soldiers"},{"name":"yam leaves ex-Space Soldiers; seeks new EU challenge","link":"/news/26640/yam-leaves-ex-space-soldiers-seeks-new-eu-challenge"},{"name":"Calyx open to offers","link":"/news/26639/calyx-open-to-offers"},{"name":"ESL Pro League S9 Group A day 1 recap","link":"/news/26569/esl-pro-league-s9-group-a-day-1-recap"},{"name":"North and OpTic through to Europe Minor","link":"/news/25626/north-and-optic-through-to-europe-minor"},{"name":"Space Soldiers players part ways with organization","link":"/news/25083/space-soldiers-players-part-ways-with-organization"},{"name":"Player stock shift: September","link":"/news/24972/player-stock-shift-september"},{"name":"MIBR take down Virtus.pro to secure grand final spot; Cloud9 beat Space Soldiers","link":"/news/24942/mibr-take-down-virtuspro-to-secure-grand-final-spot-cloud9-beat-space-soldiers"},{"name":"FACEIT Major New Challengers Stage preview: Returning Challengers\t","link":"/news/24626/faceit-major-new-challengers-stage-preview-returning-challengers"},{"name":"ESL One Belo Horizonte key storylines","link":"/news/23927/esl-one-belo-horizonte-key-storylines"},{"name":"Player stock shift: May","link":"/news/23863/player-stock-shift-may"},{"name":"Space Soldiers defeat Rogue to win Dreamhack Open Austin","link":"/news/23840/space-soldiers-defeat-rogue-to-win-dreamhack-open-austin"},{"name":"Space Soldiers beat Heroic; to DH Austin grand final","link":"/news/23835/space-soldiers-beat-heroic-to-dh-austin-grand-final"},{"name":"Rogue slam Space Soldiers to advance to DH Austin playoffs","link":"/news/23816/rogue-slam-space-soldiers-to-advance-to-dh-austin-playoffs"},{"name":"Winners and losers of ESL Pro League Season 7 Finals","link":"/news/23709/winners-and-losers-of-esl-pro-league-season-7-finals"},{"name":"Heroic, Space Soldiers & compLexity invited to DreamHack Open Austin","link":"/news/23643/heroic-space-soldiers-complexity-invited-to-dreamhack-open-austin"},{"name":"MAJ3R: \"We thought about [skipping the event], but then we asked DESPE on the last day\"","link":"/news/23603/maj3r-we-thought-about-skipping-the-event-but-then-we-asked-despe-on-the-last-day"},{"name":"Space Soldiers, Liquid overrun Renegades, Grayhound","link":"/news/23600/space-soldiers-liquid-overrun-renegades-grayhound"},{"name":"DESPE to stand in for Calyx at EPL S7 Finals","link":"/news/23586/despe-to-stand-in-for-calyx-at-epl-s7-finals"},{"name":"DreamHack Masters Marseille preview","link":"/news/23312/dreamhack-masters-marseille-preview"},{"name":"Team Ranking: March 2018","link":"/news/23193/team-ranking-march-2018"},{"name":"Valiance, Space Soldiers qualify for DreamHack Masters Marseille","link":"/news/23139/valiance-space-soldiers-qualify-for-dreamhack-masters-marseille"},{"name":"fnatic beat Space Soldiers to win WESG World Finals","link":"/news/23082/fnatic-beat-space-soldiers-to-win-wesg-world-finals"},{"name":"Player stock shift: January","link":"/news/22732/player-stock-shift-january"},{"name":"Team Ranking: January 2018","link":"/news/22706/team-ranking-january-2018"},{"name":"mousesports edge past Space Soldiers to qualify for Major playoffs","link":"/news/22592/mousesports-edge-past-space-soldiers-to-qualify-for-major-playoffs"},{"name":"SK secure hard-fought victory over Space Soldiers","link":"/news/22540/sk-secure-hard-fought-victory-over-space-soldiers"},{"name":"nitr0: \"We already surpassed our goal making top 16\"","link":"/news/22507/nitr0-we-already-surpassed-our-goal-making-top-16"},{"name":"Calyx: \"These four days were the most important time in our lives\"","link":"/news/22491/calyx-these-four-days-were-the-most-important-time-in-our-lives"},{"name":"Space Soldiers qualify for Major after beating mousesports in OT","link":"/news/22487/space-soldiers-qualify-for-major-after-beating-mousesports-in-ot"},{"name":"AGO win ESEA S26 MDL Global Challenge over Space Soldiers","link":"/news/22397/ago-win-esea-s26-mdl-global-challenge-over-space-soldiers"},{"name":"Space Soldiers beat eXtatus; advance to MDL final","link":"/news/22392/space-soldiers-beat-extatus-advance-to-mdl-final"},{"name":"AGO beat Space Soldiers; into ESEA MDL GC playoffs","link":"/news/22384/ago-beat-space-soldiers-into-esea-mdl-gc-playoffs"},{"name":"DESPE to stand in for Space Soldiers at WESG EU & CIS Finals","link":"/news/22080/despe-to-stand-in-for-space-soldiers-at-wesg-eu-cis-finals"},{"name":"Space Soldiers beat Virtus.pro to qualify for ESEA GC & EPL Relegation","link":"/news/22053/space-soldiers-beat-virtuspro-to-qualify-for-esea-gc-epl-relegation"},{"name":"North Academy defeat Space Soldiers; qualify for DH Winter","link":"/news/22007/north-academy-defeat-space-soldiers-qualify-for-dh-winter"},{"name":"Space Soldiers win EU Minor final after defeating EnVyUs 2-0","link":"/news/21957/space-soldiers-win-eu-minor-final-after-defeating-envyus-2-0"},{"name":"Space Soldiers beat OpTic; book Major Qualifier spot","link":"/news/21951/space-soldiers-beat-optic-book-major-qualifier-spot"},{"name":"Calyx: \"We reminded ourselves that we need to play our game, only our game\"","link":"/news/21950/calyx-we-reminded-ourselves-that-we-need-to-play-our-game-only-our-game"},{"name":"Space Soldiers book last playoff spot over PRIDE","link":"/news/21938/space-soldiers-book-last-playoff-spot-over-pride"},{"name":"Europe Minor Preview","link":"/news/21906/europe-minor-preview"},{"name":"Space Soldiers qualify for SL i-League Invitational Shanghai","link":"/news/21721/space-soldiers-qualify-for-sl-i-league-invitational-shanghai"},{"name":"ESL One Cologne 2017 Preview","link":"/news/20883/esl-one-cologne-2017-preview"},{"name":"shox & kennyS win HTC 2v2","link":"/news/20468/shox-kennys-win-htc-2v2"},{"name":"XANTARES: Consider moving to EU","link":"/news/20462/xantares-consider-moving-to-eu"},{"name":"JUGi: really good IGLs in Denmark","link":"/news/20457/jugi-really-good-igls-in-denmark"},{"name":"aizy & cajunb to HTC 2v2","link":"/news/20434/aizy-cajunb-to-htc-2v2"},{"name":"ex-DarkPassage confirm disbandment","link":"/news/20432/ex-darkpassage-confirm-disbandment"},{"name":"XANTARES & Calyx to HTC 2v2","link":"/news/20367/xantares-calyx-to-htc-2v2"},{"name":"Space Soldiers invited to 4Gamers","link":"/news/20256/space-soldiers-invited-to-4gamers"},{"name":"CPH Games: 5 players to watch out for","link":"/news/20232/cph-games-5-players-to-watch-out-for"},{"name":"Virtus.pro through to ECS Season 3","link":"/news/20076/virtuspro-through-to-ecs-season-3"},{"name":"Calyx joins Space Soldiers","link":"/news/19833/calyx-joins-space-soldiers"},{"name":"ex-DP players looking for new home","link":"/news/19779/ex-dp-players-looking-for-new-home"},{"name":"iNation win Balkan Pro League","link":"/news/19399/ination-win-balkan-pro-league"},{"name":"DHW closed qualifier teams found","link":"/news/18963/dhw-closed-qualifier-teams-found"},{"name":"Turkey defeat France, on to the final","link":"/news/18907/turkey-defeat-france-on-to-the-final"},{"name":"Turkey and France to TWC semi-final","link":"/news/18896/turkey-and-france-to-twc-semi-final"},{"name":"XANTARES: \"Calyx is so good\"","link":"/news/18895/xantares-calyx-is-so-good"},{"name":"TWC teams and format announced","link":"/news/18845/twc-teams-and-format-announced"},{"name":"DarkPassage to WESG Finals","link":"/news/18531/darkpassage-to-wesg-finals"},{"name":"Video: Calyx vs. Swift","link":"/news/18522/video-calyx-vs-swift"},{"name":"asmo joins DarkPassage","link":"/news/17950/asmo-joins-darkpassage"}]}