[{"mapStatsId":212133,"date":1761676200000,"map":"de_train","team1":{"id":12818,"name":"FAVBET"},"team2":{"id":13485,"name":"VRSoholics"},"event":{"id":8774,"name":"CCT Season 3 Europe Series 10"},"result":{"team1":13,"team2":1}},{"mapStatsId":212131,"date":1761676200000,"map":"de_overpass","team1":{"id":12818,"name":"FAVBET"},"team2":{"id":13485,"name":"VRSoholics"},"event":{"id":8774,"name":"CCT Season 3 Europe Series 10"},"result":{"team1":13,"team2":4}},{"mapStatsId":212116,"date":1761676200000,"map":"de_dust2","team1":{"id":13485,"name":"VRSoholics"},"team2":{"id":12818,"name":"FAVBET"},"event":{"id":8774,"name":"CCT Season 3 Europe Series 10"},"result":{"team1":13,"team2":10}},{"mapStatsId":212128,"date":1761675900000,"map":"de_mirage","team1":{"id":9215,"name":"MIBR"},"team2":{"id":4991,"name":"fnatic"},"event":{"id":8046,"name":"PGL Masters Bucharest 2025"},"result":{"team1":5,"team2":13}},{"mapStatsId":212114,"date":1761675900000,"map":"de_inferno","team1":{"id":4991,"name":"fnatic"},"team2":{"id":9215,"name":"MIBR"},"event":{"id":8046,"name":"PGL Masters Bucharest 2025"},"result":{"team1":13,"team2":3}},{"mapStatsId":212129,"date":1761675600000,"map":"de_ancient","team1":{"id":4548,"name":"CPH Wolves"},"team2":{"id":13369,"name":"The Glecs"},"event":{"id":8797,"name":"Galaxy Battle 2025 Phase 5 Closed Qualifier"},"result":{"team1":13,"team2":4}},{"mapStatsId":212118,"date":1761675600000,"map":"de_train","team1":{"id":13369,"name":"The Glecs"},"team2":{"id":4548,"name":"CPH Wolves"},"event":{"id":8797,"name":"Galaxy Battle 2025 Phase 5 Closed Qualifier"},"result":{"team1":13,"team2":16}},{"mapStatsId":212125,"date":1761675600000,"map":"de_nuke","team1":{"id":12858,"name":"kONO"},"team2":{"id":11712,"name":"Sashi"},"event":{"id":8766,"name":"CCT Season 3 Europe Series 9"},"result":{"team1":5,"team2":13}},{"mapStatsId":212110,"date":1761675600000,"map":"de_inferno","team1":{"id":11712,"name":"Sashi"},"team2":{"id":12858,"name":"kONO"},"event":{"id":8766,"name":"CCT Season 3 Europe Series 9"},"result":{"team1":13,"team2":6}},{"mapStatsId":212134,"date":1761674400000,"map":"de_ancient","team1":{"id":7969,"name":"Nemiga"},"team2":{"id":13419,"name":"Venom"},"event":{"id":8778,"name":"ESL Challenger League Season 50 Europe Cup 4"},"result":{"team1":12,"team2":16}},{"mapStatsId":212126,"date":1761674400000,"map":"de_train","team1":{"id":7969,"name":"Nemiga"},"team2":{"id":13419,"name":"Venom"},"event":{"id":8778,"name":"ESL Challenger League Season 50 Europe Cup 4"},"result":{"team1":9,"team2":13}},{"mapStatsId":212113,"date":1761674400000,"map":"de_dust2","team1":{"id":13419,"name":"Venom"},"team2":{"id":7969,"name":"Nemiga"},"event":{"id":8778,"name":"ESL Challenger League Season 50 Europe Cup 4"},"result":{"team1":11,"team2":13}},{"mapStatsId":212132,"date":1761674400000,"map":"de_ancient","team1":{"id":7187,"name":"Nexus"},"team2":{"id":12812,"name":"ALLINNERS"},"event":{"id":8778,"name":"ESL Challenger League Season 50 Europe Cup 4"},"result":{"team1":8,"team2":13}},{"mapStatsId":212124,"date":1761674400000,"map":"de_dust2","team1":{"id":12812,"name":"ALLINNERS"},"team2":{"id":7187,"name":"Nexus"},"event":{"id":8778,"name":"ESL Challenger League Season 50 Europe Cup 4"},"result":{"team1":5,"team2":13}},{"mapStatsId":212109,"date":1761674400000,"map":"de_mirage","team1":{"id":7187,"name":"Nexus"},"team2":{"id":12812,"name":"ALLINNERS"},"event":{"id":8778,"name":"ESL Challenger League Season 50 Europe Cup 4"},"result":{"team1":6,"team2":13}},{"mapStatsId":212130,"date":1761674400000,"map":"de_nuke","team1":{"id":13380,"name":"9BOOMPRO"},"team2":{"id":10333,"name":"Sangal"},"event":{"id":8778,"name":"ESL Challenger League Season 50 Europe Cup 4"},"result":{"team1":5,"team2":13}},{"mapStatsId":212117,"date":1761674400000,"map":"de_overpass","team1":{"id":13380,"name":"9BOOMPRO"},"team2":{"id":10333,"name":"Sangal"},"event":{"id":8778,"name":"ESL Challenger League Season 50 Europe Cup 4"},"result":{"team1":6,"team2":13}},{"mapStatsId":212104,"date":1761674400000,"map":"de_mirage","team1":{"id":10333,"name":"Sangal"},"team2":{"id":13380,"name":"9BOOMPRO"},"event":{"id":8778,"name":"ESL Challenger League Season 50 Europe Cup 4"},"result":{"team1":2,"team2":13}},{"mapStatsId":212127,"date":1761674400000,"map":"de_train","team1":{"id":11251,"name":"Eternal Fire"},"team2":{"id":10621,"name":"1win"},"event":{"id":8778,"name":"ESL Challenger League Season 50 Europe Cup 4"},"result":{"team1":9,"team2":13}},{"mapStatsId":212108,"date":1761674400000,"map":"de_dust2","team1":{"id":10621,"name":"1win"},"team2":{"id":11251,"name":"Eternal Fire"},"event":{"id":8778,"name":"ESL Challenger League Season 50 Europe Cup 4"},"result":{"team1":13,"team2":8}},{"mapStatsId":212123,"date":1761674400000,"map":"de_train","team1":{"id":13181,"name":"BASEMENT BOYS"},"team2":{"id":13297,"name":"TPuDCATb TPu"},"event":{"id":8778,"name":"ESL Challenger League Season 50 Europe Cup 4"},"result":{"team1":2,"team2":13}},{"mapStatsId":212111,"date":1761674400000,"map":"de_ancient","team1":{"id":13297,"name":"TPuDCATb TPu"},"team2":{"id":13181,"name":"BASEMENT BOYS"},"event":{"id":8778,"name":"ESL Challenger League Season 50 Europe Cup 4"},"result":{"team1":16,"team2":13}},{"mapStatsId":212121,"date":1761674400000,"map":"de_nuke","team1":{"id":12895,"name":"K27"},"team2":{"id":11811,"name":"Monte"},"event":{"id":8778,"name":"ESL Challenger League Season 50 Europe Cup 4"},"result":{"team1":8,"team2":13}},{"mapStatsId":212107,"date":1761674400000,"map":"de_dust2","team1":{"id":11811,"name":"Monte"},"team2":{"id":12895,"name":"K27"},"event":{"id":8778,"name":"ESL Challenger League Season 50 Europe Cup 4"},"result":{"team1":13,"team2":4}},{"mapStatsId":212120,"date":1761674400000,"map":"de_mirage","team1":{"id":12857,"name":"FORZE Reload"},"team2":{"id":10459,"name":"ARCRED"},"event":{"id":8778,"name":"ESL Challenger League Season 50 Europe Cup 4"},"result":{"team1":13,"team2":10}},{"mapStatsId":212106,"date":1761674400000,"map":"de_nuke","team1":{"id":10459,"name":"ARCRED"},"team2":{"id":12857,"name":"FORZE Reload"},"event":{"id":8778,"name":"ESL Challenger League Season 50 Europe Cup 4"},"result":{"team1":6,"team2":13}},{"mapStatsId":212115,"date":1761674400000,"map":"de_train","team1":{"id":12960,"name":"Fire Flux"},"team2":{"id":13483,"name":"Washington"},"event":{"id":8794,"name":"NODWIN Clutch Series 2 Closed Qualifier"},"result":{"team1":13,"team2":4}},{"mapStatsId":212105,"date":1761674400000,"map":"de_ancient","team1":{"id":13483,"name":"Washington"},"team2":{"id":12960,"name":"Fire Flux"},"event":{"id":8794,"name":"NODWIN Clutch Series 2 Closed Qualifier"},"result":{"team1":5,"team2":13}},{"mapStatsId":212098,"date":1761666900000,"map":"de_ancient","team1":{"id":13470,"name":"Oramond"},"team2":{"id":13027,"name":"Nuclear TigeRES"},"event":{"id":8774,"name":"CCT Season 3 Europe Series 10"},"result":{"team1":13,"team2":10}},{"mapStatsId":212091,"date":1761666900000,"map":"de_mirage","team1":{"id":13027,"name":"Nuclear TigeRES"},"team2":{"id":13470,"name":"Oramond"},"event":{"id":8774,"name":"CCT Season 3 Europe Series 10"},"result":{"team1":6,"team2":13}},{"mapStatsId":212103,"date":1761664200000,"map":"de_ancient","team1":{"id":4411,"name":"Ninjas in Pyjamas"},"team2":{"id":13404,"name":"Gentle Mates"},"event":{"id":8046,"name":"PGL Masters Bucharest 2025"},"result":{"team1":10,"team2":13}},{"mapStatsId":212096,"date":1761664200000,"map":"de_train","team1":{"id":13404,"name":"Gentle Mates"},"team2":{"id":4411,"name":"Ninjas in Pyjamas"},"event":{"id":8046,"name":"PGL Masters Bucharest 2025"},"result":{"team1":9,"team2":13}},{"mapStatsId":212090,"date":1761664200000,"map":"de_inferno","team1":{"id":4411,"name":"Ninjas in Pyjamas"},"team2":{"id":13404,"name":"Gentle Mates"},"event":{"id":8046,"name":"PGL Masters Bucharest 2025"},"result":{"team1":9,"team2":13}},{"mapStatsId":212100,"date":1761664200000,"map":"de_dust2","team1":{"id":11609,"name":"GenOne"},"team2":{"id":7865,"name":"HAVU"},"event":{"id":8794,"name":"NODWIN Clutch Series 2 Closed Qualifier"},"result":{"team1":13,"team2":2}},{"mapStatsId":212094,"date":1761664200000,"map":"de_inferno","team1":{"id":7865,"name":"HAVU"},"team2":{"id":11609,"name":"GenOne"},"event":{"id":8794,"name":"NODWIN Clutch Series 2 Closed Qualifier"},"result":{"team1":8,"team2":13}},{"mapStatsId":212089,"date":1761664200000,"map":"de_nuke","team1":{"id":11609,"name":"GenOne"},"team2":{"id":7865,"name":"HAVU"},"event":{"id":8794,"name":"NODWIN Clutch Series 2 Closed Qualifier"},"result":{"team1":5,"team2":13}},{"mapStatsId":212102,"date":1761663600000,"map":"de_nuke","team1":{"id":12858,"name":"kONO"},"team2":{"id":13501,"name":"illwill"},"event":{"id":8797,"name":"Galaxy Battle 2025 Phase 5 Closed Qualifier"},"result":{"team1":13,"team2":8}},{"mapStatsId":212097,"date":1761663600000,"map":"de_dust2","team1":{"id":12858,"name":"kONO"},"team2":{"id":13501,"name":"illwill"},"event":{"id":8797,"name":"Galaxy Battle 2025 Phase 5 Closed Qualifier"},"result":{"team1":8,"team2":13}},{"mapStatsId":212088,"date":1761663600000,"map":"de_overpass","team1":{"id":13501,"name":"illwill"},"team2":{"id":12858,"name":"kONO"},"event":{"id":8797,"name":"Galaxy Battle 2025 Phase 5 Closed Qualifier"},"result":{"team1":9,"team2":13}},{"mapStatsId":212099,"date":1761663600000,"map":"de_dust2","team1":{"id":12431,"name":"Betera"},"team2":{"id":7187,"name":"Nexus"},"event":{"id":8766,"name":"CCT Season 3 Europe Series 9"},"result":{"team1":13,"team2":9}},{"mapStatsId":212092,"date":1761663600000,"map":"de_ancient","team1":{"id":7187,"name":"Nexus"},"team2":{"id":12431,"name":"Betera"},"event":{"id":8766,"name":"CCT Season 3 Europe Series 9"},"result":{"team1":13,"team2":4}},{"mapStatsId":212085,"date":1761663600000,"map":"de_train","team1":{"id":12431,"name":"Betera"},"team2":{"id":7187,"name":"Nexus"},"event":{"id":8766,"name":"CCT Season 3 Europe Series 9"},"result":{"team1":13,"team2":7}},{"mapStatsId":212095,"date":1761663600000,"map":"de_nuke","team1":{"id":10245,"name":"JiJieHao"},"team2":{"id":11641,"name":"Metizport"},"event":{"id":8772,"name":"Winline Insight Season 9"},"result":{"team1":13,"team2":9}},{"mapStatsId":212087,"date":1761663600000,"map":"de_dust2","team1":{"id":10245,"name":"JiJieHao"},"team2":{"id":11641,"name":"Metizport"},"event":{"id":8772,"name":"Winline Insight Season 9"},"result":{"team1":13,"team2":4}},{"mapStatsId":212093,"date":1761663600000,"map":"de_mirage","team1":{"id":4773,"name":"paiN"},"team2":{"id":11241,"name":"B8"},"event":{"id":8046,"name":"PGL Masters Bucharest 2025"},"result":{"team1":13,"team2":10}},{"mapStatsId":212086,"date":1761663600000,"map":"de_dust2","team1":{"id":11241,"name":"B8"},"team2":{"id":4773,"name":"paiN"},"event":{"id":8046,"name":"PGL Masters Bucharest 2025"},"result":{"team1":8,"team2":13}},{"mapStatsId":212081,"date":1761656100000,"map":"de_inferno","team1":{"id":7175,"name":"HEROIC"},"team2":{"id":11861,"name":"Aurora"},"event":{"id":8046,"name":"PGL Masters Bucharest 2025"},"result":{"team1":13,"team2":11}},{"mapStatsId":212073,"date":1761656100000,"map":"de_mirage","team1":{"id":11861,"name":"Aurora"},"team2":{"id":7175,"name":"HEROIC"},"event":{"id":8046,"name":"PGL Masters Bucharest 2025"},"result":{"team1":4,"team2":13}},{"mapStatsId":212084,"date":1761654600000,"map":"de_mirage","team1":{"id":10459,"name":"ARCRED"},"team2":{"id":13178,"name":"NOVAQ"},"event":{"id":8774,"name":"CCT Season 3 Europe Series 10"},"result":{"team1":13,"team2":7}},{"mapStatsId":212080,"date":1761654600000,"map":"de_train","team1":{"id":13178,"name":"NOVAQ"},"team2":{"id":10459,"name":"ARCRED"},"event":{"id":8774,"name":"CCT Season 3 Europe Series 10"},"result":{"team1":13,"team2":11}},{"mapStatsId":212074,"date":1761654600000,"map":"de_inferno","team1":{"id":10459,"name":"ARCRED"},"team2":{"id":13178,"name":"NOVAQ"},"event":{"id":8774,"name":"CCT Season 3 Europe Series 10"},"result":{"team1":16,"team2":14}},{"mapStatsId":212083,"date":1761653700000,"map":"de_nuke","team1":{"id":13251,"name":"Mousquetaires"},"team2":{"id":9621,"name":"AaB"},"event":{"id":8794,"name":"NODWIN Clutch Series 2 Closed Qualifier"},"result":{"team1":13,"team2":5}},{"mapStatsId":212077,"date":1761653700000,"map":"de_ancient","team1":{"id":13251,"name":"Mousquetaires"},"team2":{"id":9621,"name":"AaB"},"event":{"id":8794,"name":"NODWIN Clutch Series 2 Closed Qualifier"},"result":{"team1":13,"team2":7}},{"mapStatsId":212071,"date":1761653700000,"map":"de_dust2","team1":{"id":9621,"name":"AaB"},"team2":{"id":13251,"name":"Mousquetaires"},"event":{"id":8794,"name":"NODWIN Clutch Series 2 Closed Qualifier"},"result":{"team1":13,"team2":8}},{"mapStatsId":212082,"date":1761653100000,"map":"de_dust2","team1":{"id":4914,"name":"3DMAX"},"team2":{"id":12774,"name":"FlyQuest"},"event":{"id":8046,"name":"PGL Masters Bucharest 2025"},"result":{"team1":10,"team2":13}},{"mapStatsId":212076,"date":1761653100000,"map":"de_inferno","team1":{"id":12774,"name":"FlyQuest"},"team2":{"id":4914,"name":"3DMAX"},"event":{"id":8046,"name":"PGL Masters Bucharest 2025"},"result":{"team1":8,"team2":13}},{"mapStatsId":212069,"date":1761653100000,"map":"de_train","team1":{"id":4914,"name":"3DMAX"},"team2":{"id":12774,"name":"FlyQuest"},"event":{"id":8046,"name":"PGL Masters Bucharest 2025"},"result":{"team1":9,"team2":13}},{"mapStatsId":212078,"date":1761652800000,"map":"de_mirage","team1":{"id":12604,"name":"Johnny Speeds"},"team2":{"id":12380,"name":"CYBERSHOKE"},"event":{"id":8766,"name":"CCT Season 3 Europe Series 9"},"result":{"team1":13,"team2":16}},{"mapStatsId":212070,"date":1761652800000,"map":"de_nuke","team1":{"id":12380,"name":"CYBERSHOKE"},"team2":{"id":12604,"name":"Johnny Speeds"},"event":{"id":8766,"name":"CCT Season 3 Europe Series 9"},"result":{"team1":13,"team2":7}},{"mapStatsId":212072,"date":1761652800000,"map":"de_mirage","team1":{"id":7187,"name":"Nexus"},"team2":{"id":11737,"name":"EYEBALLERS"},"event":{"id":8772,"name":"Winline Insight Season 9"},"result":{"team1":11,"team2":13}},{"mapStatsId":212068,"date":1761652800000,"map":"de_nuke","team1":{"id":11737,"name":"EYEBALLERS"},"team2":{"id":7187,"name":"Nexus"},"event":{"id":8772,"name":"Winline Insight Season 9"},"result":{"team1":13,"team2":1}},{"mapStatsId":212067,"date":1761647700000,"map":"de_nuke","team1":{"id":12468,"name":"Legacy"},"team2":{"id":6665,"name":"Astralis"},"event":{"id":8046,"name":"PGL Masters Bucharest 2025"},"result":{"team1":13,"team2":3}},{"mapStatsId":212064,"date":1761647700000,"map":"de_inferno","team1":{"id":6665,"name":"Astralis"},"team2":{"id":12468,"name":"Legacy"},"event":{"id":8046,"name":"PGL Masters Bucharest 2025"},"result":{"team1":14,"team2":16}},{"mapStatsId":212066,"date":1761643800000,"map":"de_dust2","team1":{"id":13483,"name":"Washington"},"team2":{"id":9621,"name":"AaB"},"event":{"id":8774,"name":"CCT Season 3 Europe Series 10"},"result":{"team1":7,"team2":13}},{"mapStatsId":212060,"date":1761643800000,"map":"de_ancient","team1":{"id":13483,"name":"Washington"},"team2":{"id":9621,"name":"AaB"},"event":{"id":8774,"name":"CCT Season 3 Europe Series 10"},"result":{"team1":6,"team2":13}},{"mapStatsId":212057,"date":1761643800000,"map":"de_nuke","team1":{"id":9621,"name":"AaB"},"team2":{"id":13483,"name":"Washington"},"event":{"id":8774,"name":"CCT Season 3 Europe Series 10"},"result":{"team1":9,"team2":13}},{"mapStatsId":212061,"date":1761642000000,"map":"de_nuke","team1":{"id":11251,"name":"Eternal Fire"},"team2":{"id":11790,"name":"ENCE Academy"},"event":{"id":8794,"name":"NODWIN Clutch Series 2 Closed Qualifier"},"result":{"team1":11,"team2":13}},{"mapStatsId":212055,"date":1761642000000,"map":"de_dust2","team1":{"id":11790,"name":"ENCE Academy"},"team2":{"id":11251,"name":"Eternal Fire"},"event":{"id":8794,"name":"NODWIN Clutch Series 2 Closed Qualifier"},"result":{"team1":13,"team2":11}},{"mapStatsId":212062,"date":1761638400000,"map":"de_ancient","team1":{"id":9928,"name":"GamerLegion"},"team2":{"id":10567,"name":"SAW"},"event":{"id":8046,"name":"PGL Masters Bucharest 2025"},"result":{"team1":14,"team2":16}},{"mapStatsId":212054,"date":1761638400000,"map":"de_inferno","team1":{"id":10567,"name":"SAW"},"team2":{"id":9928,"name":"GamerLegion"},"event":{"id":8046,"name":"PGL Masters Bucharest 2025"},"result":{"team1":19,"team2":17}},{"mapStatsId":212052,"date":1761638400000,"map":"de_nuke","team1":{"id":9928,"name":"GamerLegion"},"team2":{"id":10567,"name":"SAW"},"event":{"id":8046,"name":"PGL Masters Bucharest 2025"},"result":{"team1":13,"team2":6}},{"mapStatsId":212058,"date":1761638400000,"map":"de_ancient","team1":{"id":12394,"name":"BetBoom"},"team2":{"id":5973,"name":"Liquid"},"event":{"id":8046,"name":"PGL Masters Bucharest 2025"},"result":{"team1":2,"team2":13}},{"mapStatsId":212053,"date":1761638400000,"map":"de_nuke","team1":{"id":5973,"name":"Liquid"},"team2":{"id":12394,"name":"BetBoom"},"event":{"id":8046,"name":"PGL Masters Bucharest 2025"},"result":{"team1":3,"team2":13}},{"mapStatsId":212051,"date":1761638400000,"map":"de_mirage","team1":{"id":12394,"name":"BetBoom"},"team2":{"id":5973,"name":"Liquid"},"event":{"id":8046,"name":"PGL Masters Bucharest 2025"},"result":{"team1":5,"team2":13}},{"mapStatsId":212050,"date":1761616800000,"map":"de_overpass","team1":{"id":10901,"name":"OverKnight"},"team2":{"id":12909,"name":"Phoenix"},"event":{"id":8780,"name":"ESL Challenger League Season 50 North America Cup 4"},"result":{"team1":13,"team2":4}},{"mapStatsId":212048,"date":1761616800000,"map":"de_train","team1":{"id":10901,"name":"OverKnight"},"team2":{"id":12909,"name":"Phoenix"},"event":{"id":8780,"name":"ESL Challenger League Season 50 North America Cup 4"},"result":{"team1":5,"team2":13}},{"mapStatsId":212044,"date":1761616800000,"map":"de_mirage","team1":{"id":12909,"name":"Phoenix"},"team2":{"id":10901,"name":"OverKnight"},"event":{"id":8780,"name":"ESL Challenger League Season 50 North America Cup 4"},"result":{"team1":12,"team2":16}},{"mapStatsId":212049,"date":1761616800000,"map":"de_overpass","team1":{"id":13328,"name":"TSG"},"team2":{"id":5479,"name":"Mythic"},"event":{"id":8780,"name":"ESL Challenger League Season 50 North America Cup 4"},"result":{"team1":7,"team2":13}},{"mapStatsId":212042,"date":1761616800000,"map":"de_nuke","team1":{"id":5479,"name":"Mythic"},"team2":{"id":13328,"name":"TSG"},"event":{"id":8780,"name":"ESL Challenger League Season 50 North America Cup 4"},"result":{"team1":13,"team2":5}},{"mapStatsId":212047,"date":1761616800000,"map":"de_ancient","team1":{"id":12908,"name":"Aether"},"team2":{"id":12534,"name":"BOSS"},"event":{"id":8780,"name":"ESL Challenger League Season 50 North America Cup 4"},"result":{"team1":8,"team2":13}},{"mapStatsId":212043,"date":1761616800000,"map":"de_dust2","team1":{"id":12534,"name":"BOSS"},"team2":{"id":12908,"name":"Aether"},"event":{"id":8780,"name":"ESL Challenger League Season 50 North America Cup 4"},"result":{"team1":13,"team2":10}},{"mapStatsId":212046,"date":1761616800000,"map":"de_nuke","team1":{"id":12164,"name":"Zomblers"},"team2":{"id":7720,"name":"InControl"},"event":{"id":8780,"name":"ESL Challenger League Season 50 North America Cup 4"},"result":{"team1":13,"team2":11}},{"mapStatsId":212041,"date":1761616800000,"map":"de_inferno","team1":{"id":7720,"name":"InControl"},"team2":{"id":12164,"name":"Zomblers"},"event":{"id":8780,"name":"ESL Challenger League Season 50 North America Cup 4"},"result":{"team1":4,"team2":13}},{"mapStatsId":212038,"date":1761607800000,"map":"de_train","team1":{"id":12554,"name":"regain"},"team2":{"id":7720,"name":"InControl"},"event":{"id":8755,"name":"Dust2.us Eagle Masters Series 4"},"result":{"team1":13,"team2":8}},{"mapStatsId":212035,"date":1761607800000,"map":"de_dust2","team1":{"id":7720,"name":"InControl"},"team2":{"id":12554,"name":"regain"},"event":{"id":8755,"name":"Dust2.us Eagle Masters Series 4"},"result":{"team1":3,"team2":13}},{"mapStatsId":212039,"date":1761602400000,"map":"de_inferno","team1":{"id":13304,"name":"LP"},"team2":{"id":11571,"name":"Gaimin Gladiators"},"event":{"id":8779,"name":"ESL Challenger League Season 50 South America Cup 4"},"result":{"team1":16,"team2":13}},{"mapStatsId":212032,"date":1761602400000,"map":"de_train","team1":{"id":13304,"name":"LP"},"team2":{"id":11571,"name":"Gaimin Gladiators"},"event":{"id":8779,"name":"ESL Challenger League Season 50 South America Cup 4"},"result":{"team1":8,"team2":13}},{"mapStatsId":212026,"date":1761602400000,"map":"de_ancient","team1":{"id":11571,"name":"Gaimin Gladiators"},"team2":{"id":13304,"name":"LP"},"event":{"id":8779,"name":"ESL Challenger League Season 50 South America Cup 4"},"result":{"team1":7,"team2":13}},{"mapStatsId":212037,"date":1761602400000,"map":"de_dust2","team1":{"id":12144,"name":"BESTIA"},"team2":{"id":13081,"name":"Fake do Biru"},"event":{"id":8779,"name":"ESL Challenger League Season 50 South America Cup 4"},"result":{"team1":13,"team2":9}},{"mapStatsId":212031,"date":1761602400000,"map":"de_inferno","team1":{"id":13081,"name":"Fake do Biru"},"team2":{"id":12144,"name":"BESTIA"},"event":{"id":8779,"name":"ESL Challenger League Season 50 South America Cup 4"},"result":{"team1":13,"team2":8}},{"mapStatsId":212028,"date":1761602400000,"map":"de_mirage","team1":{"id":12144,"name":"BESTIA"},"team2":{"id":13081,"name":"Fake do Biru"},"event":{"id":8779,"name":"ESL Challenger League Season 50 South America Cup 4"},"result":{"team1":13,"team2":11}},{"mapStatsId":212036,"date":1761602400000,"map":"de_train","team1":{"id":12548,"name":"Dusty Roots"},"team2":{"id":12677,"name":"Galorys"},"event":{"id":8779,"name":"ESL Challenger League Season 50 South America Cup 4"},"result":{"team1":3,"team2":13}},{"mapStatsId":212033,"date":1761602400000,"map":"de_nuke","team1":{"id":12677,"name":"Galorys"},"team2":{"id":12548,"name":"Dusty Roots"},"event":{"id":8779,"name":"ESL Challenger League Season 50 South America Cup 4"},"result":{"team1":13,"team2":3}},{"mapStatsId":212029,"date":1761602400000,"map":"de_ancient","team1":{"id":12548,"name":"Dusty Roots"},"team2":{"id":12677,"name":"Galorys"},"event":{"id":8779,"name":"ESL Challenger League Season 50 South America Cup 4"},"result":{"team1":16,"team2":13}},{"mapStatsId":212034,"date":1761602400000,"map":"de_ancient","team1":{"id":12776,"name":"Bounty Hunters"},"team2":{"id":6033,"name":"Keyd Stars"},"event":{"id":8779,"name":"ESL Challenger League Season 50 South America Cup 4"},"result":{"team1":13,"team2":11}},{"mapStatsId":212027,"date":1761602400000,"map":"de_nuke","team1":{"id":6033,"name":"Keyd Stars"},"team2":{"id":12776,"name":"Bounty Hunters"},"event":{"id":8779,"name":"ESL Challenger League Season 50 South America Cup 4"},"result":{"team1":5,"team2":13}},{"mapStatsId":212024,"date":1761589800000,"map":"de_train","team1":{"id":11446,"name":"Leo"},"team2":{"id":13027,"name":"Nuclear TigeRES"},"event":{"id":8773,"name":"CCT Season 3 Europe Series 10 Closed Qualifier"},"result":{"team1":10,"team2":13}},{"mapStatsId":212017,"date":1761589800000,"map":"de_dust2","team1":{"id":13027,"name":"Nuclear TigeRES"},"team2":{"id":11446,"name":"Leo"},"event":{"id":8773,"name":"CCT Season 3 Europe Series 10 Closed Qualifier"},"result":{"team1":13,"team2":5}},{"mapStatsId":212019,"date":1761589800000,"map":"de_inferno","team1":{"id":12812,"name":"ALLINNERS"},"team2":{"id":13178,"name":"NOVAQ"},"event":{"id":8778,"name":"ESL Challenger League Season 50 Europe Cup 4"},"result":{"team1":13,"team2":8}},{"mapStatsId":212004,"date":1761589800000,"map":"de_ancient","team1":{"id":13178,"name":"NOVAQ"},"team2":{"id":12812,"name":"ALLINNERS"},"event":{"id":8778,"name":"ESL Challenger League Season 50 Europe Cup 4"},"result":{"team1":10,"team2":13}},{"mapStatsId":212003,"date":1761589800000,"map":"de_mirage","team1":{"id":11446,"name":"Leo"},"team2":{"id":13027,"name":"Nuclear TigeRES"},"event":{"id":8773,"name":"CCT Season 3 Europe Series 10 Closed Qualifier"},"result":{"team1":13,"team2":7}},{"mapStatsId":212023,"date":1761588000000,"map":"de_overpass","team1":{"id":10459,"name":"ARCRED"},"team2":{"id":12694,"name":"RUBY"},"event":{"id":8778,"name":"ESL Challenger League Season 50 Europe Cup 4"},"result":{"team1":13,"team2":10}},{"mapStatsId":212016,"date":1761588000000,"map":"de_nuke","team1":{"id":10459,"name":"ARCRED"},"team2":{"id":12694,"name":"RUBY"},"event":{"id":8778,"name":"ESL Challenger League Season 50 Europe Cup 4"},"result":{"team1":8,"team2":13}},{"mapStatsId":211999,"date":1761588000000,"map":"de_train","team1":{"id":12694,"name":"RUBY"},"team2":{"id":10459,"name":"ARCRED"},"event":{"id":8778,"name":"ESL Challenger League Season 50 Europe Cup 4"},"result":{"team1":11,"team2":13}},{"mapStatsId":212020,"date":1761588000000,"map":"de_train","team1":{"id":7187,"name":"Nexus"},"team2":{"id":13465,"name":"Dziuseppe"},"event":{"id":8778,"name":"ESL Challenger League Season 50 Europe Cup 4"},"result":{"team1":13,"team2":8}},{"mapStatsId":212007,"date":1761588000000,"map":"de_mirage","team1":{"id":13465,"name":"Dziuseppe"},"team2":{"id":7187,"name":"Nexus"},"event":{"id":8778,"name":"ESL Challenger League Season 50 Europe Cup 4"},"result":{"team1":2,"team2":13}},{"mapStatsId":211998,"date":1761588000000,"map":"de_ancient","team1":{"id":7187,"name":"Nexus"},"team2":{"id":13465,"name":"Dziuseppe"},"event":{"id":8778,"name":"ESL Challenger League Season 50 Europe Cup 4"},"result":{"team1":6,"team2":13}},{"mapStatsId":212018,"date":1761588000000,"map":"de_dust2","team1":{"id":13380,"name":"9BOOMPRO"},"team2":{"id":7865,"name":"HAVU"},"event":{"id":8778,"name":"ESL Challenger League Season 50 Europe Cup 4"},"result":{"team1":13,"team2":6}},{"mapStatsId":212006,"date":1761588000000,"map":"de_mirage","team1":{"id":7865,"name":"HAVU"},"team2":{"id":13380,"name":"9BOOMPRO"},"event":{"id":8778,"name":"ESL Challenger League Season 50 Europe Cup 4"},"result":{"team1":7,"team2":13}},{"mapStatsId":211991,"date":1761588000000,"map":"de_nuke","team1":{"id":13380,"name":"9BOOMPRO"},"team2":{"id":7865,"name":"HAVU"},"event":{"id":8778,"name":"ESL Challenger League Season 50 Europe Cup 4"},"result":{"team1":3,"team2":13}},{"mapStatsId":212015,"date":1761588000000,"map":"de_overpass","team1":{"id":7441,"name":"ECLOT"},"team2":{"id":10333,"name":"Sangal"},"event":{"id":8778,"name":"ESL Challenger League Season 50 Europe Cup 4"},"result":{"team1":11,"team2":13}},{"mapStatsId":211996,"date":1761588000000,"map":"de_mirage","team1":{"id":10333,"name":"Sangal"},"team2":{"id":7441,"name":"ECLOT"},"event":{"id":8778,"name":"ESL Challenger League Season 50 Europe Cup 4"},"result":{"team1":13,"team2":10}},{"mapStatsId":212014,"date":1761588000000,"map":"de_nuke","team1":{"id":11251,"name":"Eternal Fire"},"team2":{"id":9621,"name":"AaB"},"event":{"id":8778,"name":"ESL Challenger League Season 50 Europe Cup 4"},"result":{"team1":13,"team2":7}},{"mapStatsId":212000,"date":1761588000000,"map":"de_mirage","team1":{"id":9621,"name":"AaB"},"team2":{"id":11251,"name":"Eternal Fire"},"event":{"id":8778,"name":"ESL Challenger League Season 50 Europe Cup 4"},"result":{"team1":11,"team2":13}},{"mapStatsId":212012,"date":1761588000000,"map":"de_mirage","team1":{"id":11523,"name":"Zero Tenacity"},"team2":{"id":13214,"name":"SPARTA"},"event":{"id":8766,"name":"CCT Season 3 Europe Series 9"},"result":{"team1":16,"team2":14}},{"mapStatsId":211992,"date":1761588000000,"map":"de_dust2","team1":{"id":13214,"name":"SPARTA"},"team2":{"id":11523,"name":"Zero Tenacity"},"event":{"id":8766,"name":"CCT Season 3 Europe Series 9"},"result":{"team1":4,"team2":13}},{"mapStatsId":212011,"date":1761588000000,"map":"de_dust2","team1":{"id":10621,"name":"1win"},"team2":{"id":10245,"name":"JiJieHao"},"event":{"id":8778,"name":"ESL Challenger League Season 50 Europe Cup 4"},"result":{"team1":13,"team2":9}},{"mapStatsId":211993,"date":1761588000000,"map":"de_inferno","team1":{"id":10245,"name":"JiJieHao"},"team2":{"id":10621,"name":"1win"},"event":{"id":8778,"name":"ESL Challenger League Season 50 Europe Cup 4"},"result":{"team1":3,"team2":13}},{"mapStatsId":212009,"date":1761588000000,"map":"de_overpass","team1":{"id":13483,"name":"Washington"},"team2":{"id":12857,"name":"FORZE Reload"},"event":{"id":8778,"name":"ESL Challenger League Season 50 Europe Cup 4"},"result":{"team1":10,"team2":13}},{"mapStatsId":211994,"date":1761588000000,"map":"de_nuke","team1":{"id":12857,"name":"FORZE Reload"},"team2":{"id":13483,"name":"Washington"},"event":{"id":8778,"name":"ESL Challenger League Season 50 Europe Cup 4"},"result":{"team1":13,"team2":7}},{"mapStatsId":212005,"date":1761588000000,"map":"de_mirage","team1":{"id":12471,"name":"GUN5"},"team2":{"id":11790,"name":"ENCE Academy"},"event":{"id":8797,"name":"Galaxy Battle 2025 Phase 5 Closed Qualifier"},"result":{"team1":13,"team2":1}},{"mapStatsId":211995,"date":1761588000000,"map":"de_dust2","team1":{"id":11790,"name":"ENCE Academy"},"team2":{"id":12471,"name":"GUN5"},"event":{"id":8797,"name":"Galaxy Battle 2025 Phase 5 Closed Qualifier"},"result":{"team1":7,"team2":13}},{"mapStatsId":212001,"date":1761584700000,"map":"de_inferno","team1":{"id":11241,"name":"B8"},"team2":{"id":4914,"name":"3DMAX"},"event":{"id":8046,"name":"PGL Masters Bucharest 2025"},"result":{"team1":13,"team2":9}},{"mapStatsId":211989,"date":1761584700000,"map":"de_ancient","team1":{"id":4914,"name":"3DMAX"},"team2":{"id":11241,"name":"B8"},"event":{"id":8046,"name":"PGL Masters Bucharest 2025"},"result":{"team1":11,"team2":13}},{"mapStatsId":211990,"date":1761579900000,"map":"de_inferno","team1":{"id":13369,"name":"The Glecs"},"team2":{"id":12812,"name":"ALLINNERS"},"event":{"id":8773,"name":"CCT Season 3 Europe Series 10 Closed Qualifier"},"result":{"team1":10,"team2":13}},{"mapStatsId":211987,"date":1761579900000,"map":"de_ancient","team1":{"id":12812,"name":"ALLINNERS"},"team2":{"id":13369,"name":"The Glecs"},"event":{"id":8773,"name":"CCT Season 3 Europe Series 10 Closed Qualifier"},"result":{"team1":8,"team2":13}},{"mapStatsId":211978,"date":1761579900000,"map":"de_dust2","team1":{"id":13369,"name":"The Glecs"},"team2":{"id":12812,"name":"ALLINNERS"},"event":{"id":8773,"name":"CCT Season 3 Europe Series 10 Closed Qualifier"},"result":{"team1":10,"team2":13}},{"mapStatsId":211988,"date":1761579900000,"map":"de_nuke","team1":{"id":9215,"name":"MIBR"},"team2":{"id":6665,"name":"Astralis"},"event":{"id":8046,"name":"PGL Masters Bucharest 2025"},"result":{"team1":11,"team2":13}},{"mapStatsId":211977,"date":1761579900000,"map":"de_inferno","team1":{"id":6665,"name":"Astralis"},"team2":{"id":9215,"name":"MIBR"},"event":{"id":8046,"name":"PGL Masters Bucharest 2025"},"result":{"team1":13,"team2":4}},{"mapStatsId":211985,"date":1761577200000,"map":"de_nuke","team1":{"id":10867,"name":"MASONIC"},"team2":{"id":13163,"name":"ALGO"},"event":{"id":8797,"name":"Galaxy Battle 2025 Phase 5 Closed Qualifier"},"result":{"team1":16,"team2":12}},{"mapStatsId":211974,"date":1761577200000,"map":"de_train","team1":{"id":13163,"name":"ALGO"},"team2":{"id":10867,"name":"MASONIC"},"event":{"id":8797,"name":"Galaxy Battle 2025 Phase 5 Closed Qualifier"},"result":{"team1":14,"team2":16}},{"mapStatsId":211981,"date":1761577200000,"map":"de_mirage","team1":{"id":12431,"name":"Betera"},"team2":{"id":10459,"name":"ARCRED"},"event":{"id":8772,"name":"Winline Insight Season 9"},"result":{"team1":22,"team2":18}},{"mapStatsId":211976,"date":1761577200000,"map":"de_ancient","team1":{"id":10459,"name":"ARCRED"},"team2":{"id":12431,"name":"Betera"},"event":{"id":8772,"name":"Winline Insight Season 9"},"result":{"team1":6,"team2":13}},{"mapStatsId":211980,"date":1761577200000,"map":"de_train","team1":{"id":10864,"name":"VP.Prodigy"},"team2":{"id":13297,"name":"TPuDCATb TPu"},"event":{"id":8766,"name":"CCT Season 3 Europe Series 9"},"result":{"team1":11,"team2":13}},{"mapStatsId":211973,"date":1761577200000,"map":"de_dust2","team1":{"id":10864,"name":"VP.Prodigy"},"team2":{"id":13297,"name":"TPuDCATb TPu"},"event":{"id":8766,"name":"CCT Season 3 Europe Series 9"},"result":{"team1":4,"team2":13}},{"mapStatsId":211970,"date":1761573600000,"map":"de_train","team1":{"id":13175,"name":"Change The Game"},"team2":{"id":12097,"name":"Eruption"},"event":{"id":8777,"name":"ESL Challenger League Season 50 Asia-Pacific Cup 4"},"result":{"team1":13,"team2":8}},{"mapStatsId":211963,"date":1761573600000,"map":"de_dust2","team1":{"id":12097,"name":"Eruption"},"team2":{"id":13175,"name":"Change The Game"},"event":{"id":8777,"name":"ESL Challenger League Season 50 Asia-Pacific Cup 4"},"result":{"team1":7,"team2":13}},{"mapStatsId":211968,"date":1761573600000,"map":"de_mirage","team1":{"id":12825,"name":"The QUBE"},"team2":{"id":12899,"name":"FengDa"},"event":{"id":8777,"name":"ESL Challenger League Season 50 Asia-Pacific Cup 4"},"result":{"team1":11,"team2":13}},{"mapStatsId":211962,"date":1761573600000,"map":"de_nuke","team1":{"id":12899,"name":"FengDa"},"team2":{"id":12825,"name":"The QUBE"},"event":{"id":8777,"name":"ESL Challenger League Season 50 Asia-Pacific Cup 4"},"result":{"team1":13,"team2":9}},{"mapStatsId":211979,"date":1761572700000,"map":"de_dust2","team1":{"id":11861,"name":"Aurora"},"team2":{"id":5973,"name":"Liquid"},"event":{"id":8046,"name":"PGL Masters Bucharest 2025"},"result":{"team1":13,"team2":8}},{"mapStatsId":211972,"date":1761572700000,"map":"de_train","team1":{"id":5973,"name":"Liquid"},"team2":{"id":11861,"name":"Aurora"},"event":{"id":8046,"name":"PGL Masters Bucharest 2025"},"result":{"team1":4,"team2":13}},{"mapStatsId":211961,"date":1761572700000,"map":"de_mirage","team1":{"id":11861,"name":"Aurora"},"team2":{"id":5973,"name":"Liquid"},"event":{"id":8046,"name":"PGL Masters Bucharest 2025"},"result":{"team1":16,"team2":19}},{"mapStatsId":211967,"date":1761571200000,"map":"de_mirage","team1":{"id":12774,"name":"FlyQuest"},"team2":{"id":4991,"name":"fnatic"},"event":{"id":8046,"name":"PGL Masters Bucharest 2025"},"result":{"team1":13,"team2":11}},{"mapStatsId":211957,"date":1761571200000,"map":"de_inferno","team1":{"id":4991,"name":"fnatic"},"team2":{"id":12774,"name":"FlyQuest"},"event":{"id":8046,"name":"PGL Masters Bucharest 2025"},"result":{"team1":11,"team2":13}},{"mapStatsId":211969,"date":1761568200000,"map":"de_ancient","team1":{"id":12586,"name":"AMKAL"},"team2":{"id":12694,"name":"RUBY"},"event":{"id":8773,"name":"CCT Season 3 Europe Series 10 Closed Qualifier"},"result":{"team1":13,"team2":5}},{"mapStatsId":211960,"date":1761568200000,"map":"de_overpass","team1":{"id":12694,"name":"RUBY"},"team2":{"id":12586,"name":"AMKAL"},"event":{"id":8773,"name":"CCT Season 3 Europe Series 10 Closed Qualifier"},"result":{"team1":10,"team2":13}},{"mapStatsId":211951,"date":1761568200000,"map":"de_dust2","team1":{"id":12586,"name":"AMKAL"},"team2":{"id":12694,"name":"RUBY"},"event":{"id":8773,"name":"CCT Season 3 Europe Series 10 Closed Qualifier"},"result":{"team1":6,"team2":13}},{"mapStatsId":211964,"date":1761566400000,"map":"de_overpass","team1":{"id":13173,"name":"Phantom"},"team2":{"id":11176,"name":"MOUZ NXT"},"event":{"id":8794,"name":"NODWIN Clutch Series 2 Closed Qualifier"},"result":{"team1":13,"team2":8}},{"mapStatsId":211959,"date":1761566400000,"map":"de_overpass","team1":{"id":7900,"name":"Spirit Academy"},"team2":{"id":9621,"name":"AaB"},"event":{"id":8772,"name":"Winline Insight Season 9"},"result":{"team1":13,"team2":9}},{"mapStatsId":211958,"date":1761566400000,"map":"de_train","team1":{"id":12960,"name":"Fire Flux"},"team2":{"id":10459,"name":"ARCRED"},"event":{"id":8766,"name":"CCT Season 3 Europe Series 9"},"result":{"team1":7,"team2":13}},{"mapStatsId":211956,"date":1761566400000,"map":"de_nuke","team1":{"id":11176,"name":"MOUZ NXT"},"team2":{"id":13173,"name":"Phantom"},"event":{"id":8794,"name":"NODWIN Clutch Series 2 Closed Qualifier"},"result":{"team1":13,"team2":9}},{"mapStatsId":211946,"date":1761566400000,"map":"de_mirage","team1":{"id":13173,"name":"Phantom"},"team2":{"id":11176,"name":"MOUZ NXT"},"event":{"id":8794,"name":"NODWIN Clutch Series 2 Closed Qualifier"},"result":{"team1":13,"team2":8}},{"mapStatsId":211955,"date":1761566400000,"map":"de_dust2","team1":{"id":9621,"name":"AaB"},"team2":{"id":7900,"name":"Spirit Academy"},"event":{"id":8772,"name":"Winline Insight Season 9"},"result":{"team1":13,"team2":6}},{"mapStatsId":211947,"date":1761566400000,"map":"de_ancient","team1":{"id":7900,"name":"Spirit Academy"},"team2":{"id":9621,"name":"AaB"},"event":{"id":8772,"name":"Winline Insight Season 9"},"result":{"team1":13,"team2":9}},{"mapStatsId":211952,"date":1761566400000,"map":"de_dust2","team1":{"id":10459,"name":"ARCRED"},"team2":{"id":12960,"name":"Fire Flux"},"event":{"id":8766,"name":"CCT Season 3 Europe Series 9"},"result":{"team1":19,"team2":17}},{"mapStatsId":211950,"date":1761564000000,"map":"de_mirage","team1":{"id":12394,"name":"BetBoom"},"team2":{"id":7175,"name":"HEROIC"},"event":{"id":8046,"name":"PGL Masters Bucharest 2025"},"result":{"team1":11,"team2":13}},{"mapStatsId":211945,"date":1761564000000,"map":"de_nuke","team1":{"id":7175,"name":"HEROIC"},"team2":{"id":12394,"name":"BetBoom"},"event":{"id":8046,"name":"PGL Masters Bucharest 2025"},"result":{"team1":13,"team2":8}},{"mapStatsId":211948,"date":1761560100000,"map":"de_train","team1":{"id":10567,"name":"SAW"},"team2":{"id":4411,"name":"Ninjas in Pyjamas"},"event":{"id":8046,"name":"PGL Masters Bucharest 2025"},"result":{"team1":16,"team2":14}},{"mapStatsId":211944,"date":1761560100000,"map":"de_nuke","team1":{"id":4411,"name":"Ninjas in Pyjamas"},"team2":{"id":10567,"name":"SAW"},"event":{"id":8046,"name":"PGL Masters Bucharest 2025"},"result":{"team1":13,"team2":10}},{"mapStatsId":211940,"date":1761560100000,"map":"de_ancient","team1":{"id":10567,"name":"SAW"},"team2":{"id":4411,"name":"Ninjas in Pyjamas"},"event":{"id":8046,"name":"PGL Masters Bucharest 2025"},"result":{"team1":13,"team2":5}},{"mapStatsId":211942,"date":1761557400000,"map":"de_inferno","team1":{"id":12267,"name":"UNiTY"},"team2":{"id":13178,"name":"NOVAQ"},"event":{"id":8773,"name":"CCT Season 3 Europe Series 10 Closed Qualifier"},"result":{"team1":4,"team2":13}},{"mapStatsId":211937,"date":1761557400000,"map":"de_ancient","team1":{"id":13178,"name":"NOVAQ"},"team2":{"id":12267,"name":"UNiTY"},"event":{"id":8773,"name":"CCT Season 3 Europe Series 10 Closed Qualifier"},"result":{"team1":16,"team2":14}},{"mapStatsId":211943,"date":1761555600000,"map":"de_ancient","team1":{"id":12812,"name":"ALLINNERS"},"team2":{"id":13453,"name":"HubaBuba"},"event":{"id":8794,"name":"NODWIN Clutch Series 2 Closed Qualifier"},"result":{"team1":13,"team2":9}},{"mapStatsId":211939,"date":1761555600000,"map":"de_train","team1":{"id":12812,"name":"ALLINNERS"},"team2":{"id":13453,"name":"HubaBuba"},"event":{"id":8794,"name":"NODWIN Clutch Series 2 Closed Qualifier"},"result":{"team1":3,"team2":13}},{"mapStatsId":211935,"date":1761555600000,"map":"de_mirage","team1":{"id":13453,"name":"HubaBuba"},"team2":{"id":12812,"name":"ALLINNERS"},"event":{"id":8794,"name":"NODWIN Clutch Series 2 Closed Qualifier"},"result":{"team1":8,"team2":13}},{"mapStatsId":211941,"date":1761552000000,"map":"de_dust2","team1":{"id":9928,"name":"GamerLegion"},"team2":{"id":4773,"name":"paiN"},"event":{"id":8046,"name":"PGL Masters Bucharest 2025"},"result":{"team1":10,"team2":13}},{"mapStatsId":211934,"date":1761552000000,"map":"de_overpass","team1":{"id":4773,"name":"paiN"},"team2":{"id":9928,"name":"GamerLegion"},"event":{"id":8046,"name":"PGL Masters Bucharest 2025"},"result":{"team1":13,"team2":5}},{"mapStatsId":211932,"date":1761552000000,"map":"de_nuke","team1":{"id":9928,"name":"GamerLegion"},"team2":{"id":4773,"name":"paiN"},"event":{"id":8046,"name":"PGL Masters Bucharest 2025"},"result":{"team1":13,"team2":10}},{"mapStatsId":211933,"date":1761552000000,"map":"de_inferno","team1":{"id":13404,"name":"Gentle Mates"},"team2":{"id":12468,"name":"Legacy"},"event":{"id":8046,"name":"PGL Masters Bucharest 2025"},"result":{"team1":13,"team2":16}},{"mapStatsId":211931,"date":1761552000000,"map":"de_ancient","team1":{"id":12468,"name":"Legacy"},"team2":{"id":13404,"name":"Gentle Mates"},"event":{"id":8046,"name":"PGL Masters Bucharest 2025"},"result":{"team1":13,"team2":5}},{"mapStatsId":211930,"date":1761530400000,"map":"de_ancient","team1":{"id":13124,"name":"Marsborne"},"team2":{"id":12909,"name":"Phoenix"},"event":{"id":8780,"name":"ESL Challenger League Season 50 North America Cup 4"},"result":{"team1":13,"team2":9}},{"mapStatsId":211927,"date":1761530400000,"map":"de_train","team1":{"id":12909,"name":"Phoenix"},"team2":{"id":13124,"name":"Marsborne"},"event":{"id":8780,"name":"ESL Challenger League Season 50 North America Cup 4"},"result":{"team1":13,"team2":7}},{"mapStatsId":211919,"date":1761530400000,"map":"de_nuke","team1":{"id":13124,"name":"Marsborne"},"team2":{"id":12909,"name":"Phoenix"},"event":{"id":8780,"name":"ESL Challenger League Season 50 North America Cup 4"},"result":{"team1":13,"team2":9}},{"mapStatsId":211929,"date":1761530400000,"map":"de_train","team1":{"id":5479,"name":"Mythic"},"team2":{"id":11955,"name":"LAG"},"event":{"id":8780,"name":"ESL Challenger League Season 50 North America Cup 4"},"result":{"team1":9,"team2":13}},{"mapStatsId":211921,"date":1761530400000,"map":"de_nuke","team1":{"id":11955,"name":"LAG"},"team2":{"id":5479,"name":"Mythic"},"event":{"id":8780,"name":"ESL Challenger League Season 50 North America Cup 4"},"result":{"team1":13,"team2":8}},{"mapStatsId":211928,"date":1761530400000,"map":"de_mirage","team1":{"id":12908,"name":"Aether"},"team2":{"id":13499,"name":"Voca"},"event":{"id":8780,"name":"ESL Challenger League Season 50 North America Cup 4"},"result":{"team1":11,"team2":13}},{"mapStatsId":211922,"date":1761530400000,"map":"de_train","team1":{"id":13499,"name":"Voca"},"team2":{"id":12908,"name":"Aether"},"event":{"id":8780,"name":"ESL Challenger League Season 50 North America Cup 4"},"result":{"team1":13,"team2":10}},{"mapStatsId":211926,"date":1761530400000,"map":"de_mirage","team1":{"id":12164,"name":"Zomblers"},"team2":{"id":12301,"name":"FlyQuest RED"},"event":{"id":8780,"name":"ESL Challenger League Season 50 North America Cup 4"},"result":{"team1":13,"team2":11}},{"mapStatsId":211920,"date":1761530400000,"map":"de_inferno","team1":{"id":12301,"name":"FlyQuest RED"},"team2":{"id":12164,"name":"Zomblers"},"event":{"id":8780,"name":"ESL Challenger League Season 50 North America Cup 4"},"result":{"team1":6,"team2":13}},{"mapStatsId":211925,"date":1761530400000,"map":"de_ancient","team1":{"id":13328,"name":"TSG"},"team2":{"id":12554,"name":"regain"},"event":{"id":8780,"name":"ESL Challenger League Season 50 North America Cup 4"},"result":{"team1":13,"team2":10}},{"mapStatsId":211915,"date":1761530400000,"map":"de_dust2","team1":{"id":12554,"name":"regain"},"team2":{"id":13328,"name":"TSG"},"event":{"id":8780,"name":"ESL Challenger League Season 50 North America Cup 4"},"result":{"team1":5,"team2":13}},{"mapStatsId":211924,"date":1761530400000,"map":"de_ancient","team1":{"id":12534,"name":"BOSS"},"team2":{"id":7801,"name":"Ghost"},"event":{"id":8780,"name":"ESL Challenger League Season 50 North America Cup 4"},"result":{"team1":13,"team2":8}},{"mapStatsId":211917,"date":1761530400000,"map":"de_inferno","team1":{"id":12534,"name":"BOSS"},"team2":{"id":7801,"name":"Ghost"},"event":{"id":8780,"name":"ESL Challenger League Season 50 North America Cup 4"},"result":{"team1":13,"team2":3}},{"mapStatsId":211923,"date":1761530400000,"map":"de_overpass","team1":{"id":10901,"name":"OverKnight"},"team2":{"id":12190,"name":"Shimmer"},"event":{"id":8780,"name":"ESL Challenger League Season 50 North America Cup 4"},"result":{"team1":13,"team2":11}},{"mapStatsId":211916,"date":1761530400000,"map":"de_mirage","team1":{"id":12190,"name":"Shimmer"},"team2":{"id":10901,"name":"OverKnight"},"event":{"id":8780,"name":"ESL Challenger League Season 50 North America Cup 4"},"result":{"team1":9,"team2":13}},{"mapStatsId":211918,"date":1761527700000,"map":"de_mirage","team1":{"id":11660,"name":"Take Flyte"},"team2":{"id":13469,"name":"Money Crew"},"event":{"id":8755,"name":"Dust2.us Eagle Masters Series 4"},"result":{"team1":13,"team2":7}},{"mapStatsId":211914,"date":1761527700000,"map":"de_ancient","team1":{"id":13469,"name":"Money Crew"},"team2":{"id":11660,"name":"Take Flyte"},"event":{"id":8755,"name":"Dust2.us Eagle Masters Series 4"},"result":{"team1":11,"team2":13}},{"mapStatsId":211909,"date":1761523200000,"map":"de_overpass","team1":{"id":10901,"name":"OverKnight"},"team2":{"id":13294,"name":"Outfit 49"},"event":{"id":8755,"name":"Dust2.us Eagle Masters Series 4"},"result":{"team1":13,"team2":6}},{"mapStatsId":211905,"date":1761523200000,"map":"de_mirage","team1":{"id":13294,"name":"Outfit 49"},"team2":{"id":10901,"name":"OverKnight"},"event":{"id":8755,"name":"Dust2.us Eagle Masters Series 4"},"result":{"team1":7,"team2":13}}]